pyaoscx/__init__.py
pyaoscx/acl.py
pyaoscx/acl_entry.py
pyaoscx/aggregate_address.py
pyaoscx/api.py
pyaoscx/bgp_neighbor.py
pyaoscx/bgp_router.py
pyaoscx/configuration.py
pyaoscx/device.py
pyaoscx/dhcp_relay.py
pyaoscx/dns.py
pyaoscx/firmware.py
pyaoscx/interface.py
pyaoscx/ipv6.py
pyaoscx/lldp_neighbor.py
pyaoscx/mac.py
pyaoscx/object_group.py
pyaoscx/ospf_area.py
pyaoscx/ospf_interface.py
pyaoscx/ospf_router.py
pyaoscx/ospf_virtual_link.py
pyaoscx/ospfv3_router.py
pyaoscx/poe_interface.py
pyaoscx/pyaoscx_factory.py
pyaoscx/pyaoscx_module.py
pyaoscx/qos.py
pyaoscx/qos_cos.py
pyaoscx/qos_dscp.py
pyaoscx/queue.py
pyaoscx/queue_profile.py
pyaoscx/queue_profile_entry.py
pyaoscx/session.py
pyaoscx/static_mac.py
pyaoscx/static_nexthop.py
pyaoscx/static_route.py
pyaoscx/tunnel_endpoint.py
pyaoscx/vlan.py
pyaoscx/vni.py
pyaoscx/vrf.py
pyaoscx/vrf_address_family.py
pyaoscx/vsx.py
pyaoscx/exceptions/__init__.py
pyaoscx/exceptions/generic_op_error.py
pyaoscx/exceptions/login_error.py
pyaoscx/exceptions/parameter_error.py
pyaoscx/exceptions/pyaoscx_error.py
pyaoscx/exceptions/response_error.py
pyaoscx/exceptions/unsupported_capability_error.py
pyaoscx/exceptions/verification_error.py
pyaoscx/rest/__init__.py
pyaoscx/rest/v1/__init__.py
pyaoscx/rest/v1/api.py
pyaoscx/rest/v1/interface.py
pyaoscx/rest/v10_04/__init__.py
pyaoscx/rest/v10_04/api.py
pyaoscx/rest/v10_04/interface.py
pyaoscx/rest/v10_08/__init__.py
pyaoscx/rest/v10_08/api.py
pyaoscx/rest/v10_08/interface.py
pyaoscx/rest/v10_09/__init__.py
pyaoscx/rest/v10_09/api.py
pyaoscx/rest/v10_09/interface.py
pyaoscx/utils/__init__.py
pyaoscx/utils/iptools.py
pyaoscx/utils/list_attributes.py
pyaoscx/utils/util.py
workflows/__init__.py
workflows/workflow.py
pyaoscx-2.6.0.dist-info/METADATA
pyaoscx-2.6.0.dist-info/WHEEL
pyaoscx-2.6.0.dist-info/top_level.txt
pyaoscx-2.6.0.dist-info/RECORD
