Metadata-Version: 2.1
Name: pyaoscx
Version: 2.6.0
Summary: AOS-CX Python Modules
Home-page: https://github.com/aruba/pyaoscx
Author: Aruba Automation
Author-email: aruba-automation@hpe.com
License: Apache 2.0
Keywords: networking aruba aos-cx switch rest api python
Classifier: Development Status :: 5 - Production/Stable
Classifier: Intended Audience :: System Administrators
Classifier: Topic :: System :: Networking
Classifier: License :: OSI Approved :: Apache Software License
Classifier: Programming Language :: Python :: 3 :: Only
Requires-Python: >=3.6
Requires-Dist: requests
Requires-Dist: PyYAML
Requires-Dist: netaddr
Requires-Dist: requests_toolbelt
Requires-Dist: wheel
